omniblack/systemd/__init__.py
omniblack/systemd/formatter.py
omniblack/systemd/get_fds.py
omniblack.systemd-0.1.2.dist-info/WHEEL
omniblack.systemd-0.1.2.dist-info/METADATA
omniblack.systemd-0.1.2.dist-info/RECORD
