Metadata-Version: 2.1
Name: omniblack.systemd
Version: 0.1.2
Summary: Systemd integration for omniblack applications
License: AGPL-3.0-or-later
Author: Terry Patterson
Author-email: Terryp@wegrok.net
Requires-Python: >=3.9,<4.0
Classifier: License :: OSI Approved :: GNU Affero General Public License v3 or later (AGPLv3+)
Classifier: Programming Language :: Python :: 3
Requires-Dist: PyInquirer (>=1.0.3,<2.0.0)
Requires-Dist: atpublic (>=2.1.2,<3.0.0)
